staticsite/__init__.py
staticsite/__main__.py
staticsite/builder.py
staticsite/discovery.py
staticsite/plugins.py
staticsite/watcher.py
staticsite-0.1.6.dist-info/WHEEL
staticsite-0.1.6.dist-info/METADATA
staticsite-0.1.6.dist-info/RECORD
